langchain_custom_models/ChatVolcEngine.py
langchain_custom_models/__init__.py
langchain_custom_models-0.1.4.dist-info/licenses/LICENSE
langchain_custom_models-0.1.4.dist-info/METADATA
langchain_custom_models-0.1.4.dist-info/WHEEL
langchain_custom_models-0.1.4.dist-info/top_level.txt
langchain_custom_models-0.1.4.dist-info/RECORD
