Metadata-Version: 2.4
Name: langchain-custom-models
Version: 0.1.4
Summary: Custom Langchain chat models for various large model service providers
Author-email: zjp <paulzaq@yeah.net>
Project-URL: Homepage, https://github.com/Hellozaq/langchain-custom-models
Project-URL: Bug Tracker, https://github.com/Hellozaq/langchain-custom-models/issues
Keywords: langchain,volcengine,llm,agent
Classifier: Programming Language :: Python :: 3
Classifier: License :: OSI Approved :: MIT License
Classifier: Operating System :: OS Independent
Classifier: Topic :: Scientific/Engineering :: Artificial Intelligence
Requires-Python: >=3.10
License-File: LICENSE
Requires-Dist: langchain-core>=0.3.72
Requires-Dist: volcengine-python-sdk[ark]>=4.0.9
Dynamic: license-file
